kazookid/__init__.py
kazookid/substitute.py
kazookid-1.4.1.dist-info/DESCRIPTION.rst
kazookid-1.4.1.dist-info/METADATA
kazookid-1.4.1.dist-info/RECORD
kazookid-1.4.1.dist-info/WHEEL
kazookid-1.4.1.dist-info/metadata.json
kazookid-1.4.1.dist-info/top_level.txt
