Metadata-Version: 2.0
Name: kazookid
Version: 1.4.1
Summary: A simple and friendly mocking framework. Can we do more kazoo?
Home-page: https://github.com/cessor/kazookid
Author: Johannes C. Hofmeister
Author-email: py_kazookid@spam.cessor.de
License: UNKNOWN
Download-URL: https://github.com/cessor/kazookid
Platform: UNKNOWN
